{
    "creation_date": "2022-06-26T10:46:39+02:00",
    "en": {
        "show": true,
        "slug": "contact-us",
        "structure": "[{\"id\":\"8338efe4-41a2-4d3c-a23f-aaf3ea8db73b\",\"label\":\"Contact form\",\"type\":\"form\",\"object\":{\"link\":\"form_instance:kBI0IX8B2XzYoXcHXQAj\",\"label\":\"Contact form\"},\"children\":[]}]",
        "title": "Contact us"
    },
    "fr": {
        "show": true,
        "slug": "contactez-nous",
        "structure": "[]",
        "title": "Contactez-nous"
    },
    "label": "Contact form",
    "live_search": [
        "Contact us",
        "Contact form",
        "Contactez-nous"
    ],
    "title_en": [
        "Contact us"
    ],
    "title_fr": [
        "Contactez-nous"
    ],
    "type": "page"
}